MANIFEST.in
README.md
setup.py
modis/__init__.py
modis/datatools.py
modis/helptools.py
modis.egg-info/PKG-INFO
modis.egg-info/SOURCES.txt
modis.egg-info/dependency_links.txt
modis.egg-info/requires.txt
modis.egg-info/top_level.txt
modis/assets/modis.ico
modis/discord_modis/_client.py
modis/discord_modis/gui.py
modis/discord_modis/main.py
modis/discord_modis/modules/!core/_help.json
modis/discord_modis/modules/!core/_on_error.py
modis/discord_modis/modules/!core/api_core.py
modis/discord_modis/modules/!core/on_ready.py
modis/discord_modis/modules/!core/on_server_available.py
modis/discord_modis/modules/!core/on_server_join.py
modis/discord_modis/modules/!core/on_server_remove.py
modis/discord_modis/modules/_chatbot/_data.py
modis/discord_modis/modules/_chatbot/api_mitsuku.py
modis/discord_modis/modules/_chatbot/on_message.py
modis/discord_modis/modules/_tools/ui_embed.py
modis/discord_modis/modules/bethebot/_data.py
modis/discord_modis/modules/bethebot/_help.json
modis/discord_modis/modules/bethebot/_ui.py
modis/discord_modis/modules/gamedeals/_data.py
modis/discord_modis/modules/gamedeals/_help.json
modis/discord_modis/modules/gamedeals/_ui.py
modis/discord_modis/modules/gamedeals/api_reddit.py
modis/discord_modis/modules/gamedeals/on_message.py
modis/discord_modis/modules/gamedeals/ui_embed.py
modis/discord_modis/modules/help/_data.py
modis/discord_modis/modules/help/_help.json
modis/discord_modis/modules/help/api_help.py
modis/discord_modis/modules/help/on_message.py
modis/discord_modis/modules/help/ui_embed.py
modis/discord_modis/modules/hex/_data.py
modis/discord_modis/modules/hex/_help.json
modis/discord_modis/modules/hex/api_hexconvert.py
modis/discord_modis/modules/hex/on_message.py
modis/discord_modis/modules/hex/ui_embed.py
modis/discord_modis/modules/manager/_data.py
modis/discord_modis/modules/manager/_help.json
modis/discord_modis/modules/manager/api_manager.py
modis/discord_modis/modules/manager/on_message.py
modis/discord_modis/modules/manager/ui_embed.py
modis/discord_modis/modules/music/_data.py
modis/discord_modis/modules/music/_help.json
modis/discord_modis/modules/music/_musicplayer.py
