Metadata-Version: 1.2
Name: modis
Version: 0.3.2a2
Summary: A modular Discord bot
Home-page: https://github.com/Infraxion/modis/
Author: Infraxion and YtnomSnrub
Author-email: jalaunder@gmail.com
License: Apache
Keywords: modis discord bot music
Platform: UNKNOWN
Classifier: Development Status :: 4 - Beta
Classifier: Intended Audience :: Developers
Classifier: Topic :: Communications :: Chat
Classifier: License :: OSI Approved :: Apache Software License
Classifier: Programming Language :: Python :: 3.6
Requires-Python: >=3.6, <4
